baboossh/__init__.py
baboossh/connection.py
baboossh/creds.py
baboossh/db.py
baboossh/endpoint.py
baboossh/exceptions.py
baboossh/extensions.py
baboossh/host.py
baboossh/path.py
baboossh/shell.py
baboossh/tag.py
baboossh/tunnel.py
baboossh/user.py
baboossh/utils.py
baboossh/version.py
baboossh/workspace.py
baboossh/ext_dir/auth_password.py
baboossh/ext_dir/auth_privkey.py
baboossh/ext_dir/export_comprograph.py
baboossh/ext_dir/import-textlist.py
baboossh/ext_dir/import_nmapxml.py
baboossh/ext_dir/payload_exec.py
baboossh/ext_dir/payload_gather.py
baboossh/ext_dir/payload_getfile.py
baboossh/ext_dir/payload_putfile.py
baboossh/ext_dir/payload_shell.py
baboossh-1.2.1.data/scripts/baboossh
baboossh-1.2.1.dist-info/LICENSE
baboossh-1.2.1.dist-info/METADATA
baboossh-1.2.1.dist-info/WHEEL
baboossh-1.2.1.dist-info/top_level.txt
baboossh-1.2.1.dist-info/RECORD
