Metadata-Version: 2.1
Name: baboossh
Version: 1.2.1
Summary: SSH spreader made easy for red teams in a hurry
Home-page: https://github.com/cybiere/BabooSSH
Author: Cybiere - Akerva
Author-email: nicolas@cosnard.io
Project-URL: Bug Tracker, https://github.com/cybiere/BabooSSH/issues
Project-URL: Documentation, https://baboossh.cybiere.fr/
Project-URL: Source Code, https://github.com/cybiere/BabooSSH
Keywords: ssh spread redteam pentest
Classifier: Programming Language :: Python :: 3.5
Classifier: License :: OSI Approved :: GNU General Public License v3 (GPLv3)
Classifier: Environment :: Console
Classifier: Natural Language :: English
Classifier: Operating System :: POSIX
Classifier: Topic :: Security
License-File: LICENSE
Requires-Dist: cmd2
Requires-Dist: tabulate
Requires-Dist: paramiko
Requires-Dist: python-libnmap
